Metadata-Version: 1.0
Name: scanports
Version: 0.4
Summary: Ivan_Medik Library
Home-page: UNKNOWN
Author: UNKNOWN
Author-email: myofficial.acaunt@gmail.com
License: UNKNOWN
Platform: UNKNOWN
